README.md
fraclab_sdk/__init__.py
fraclab_sdk/algorithm/__init__.py
fraclab_sdk/algorithm/export.py
fraclab_sdk/algorithm/library.py
fraclab_sdk/cli.py
fraclab_sdk/config.py
fraclab_sdk/devkit/__init__.py
fraclab_sdk/devkit/compile.py
fraclab_sdk/devkit/export.py
fraclab_sdk/devkit/validate.py
fraclab_sdk/errors.py
fraclab_sdk/materialize/__init__.py
fraclab_sdk/materialize/fsops.py
fraclab_sdk/materialize/hash.py
fraclab_sdk/materialize/materializer.py
fraclab_sdk/models/__init__.py
fraclab_sdk/models/bundle_manifest.py
fraclab_sdk/models/dataspec.py
fraclab_sdk/models/drs.py
fraclab_sdk/models/output_contract.py
fraclab_sdk/models/run_output_manifest.py
fraclab_sdk/results/__init__.py
fraclab_sdk/results/preview.py
fraclab_sdk/results/reader.py
fraclab_sdk/run/__init__.py
fraclab_sdk/run/logs.py
fraclab_sdk/run/manager.py
fraclab_sdk/run/subprocess_runner.py
fraclab_sdk/runtime/__init__.py
fraclab_sdk/runtime/artifacts.py
fraclab_sdk/runtime/data_client.py
fraclab_sdk/runtime/runner_main.py
fraclab_sdk/runtime/snapshot_provider.py
fraclab_sdk/selection/__init__.py
fraclab_sdk/selection/model.py
fraclab_sdk/selection/validate.py
fraclab_sdk/snapshot/__init__.py
fraclab_sdk/snapshot/index.py
fraclab_sdk/snapshot/library.py
fraclab_sdk/snapshot/loader.py
fraclab_sdk/specs/__init__.py
fraclab_sdk/specs/manifest.py
fraclab_sdk/specs/output.py
fraclab_sdk/utils/io.py
fraclab_sdk/workbench/Home.py
fraclab_sdk/workbench/__init__.py
fraclab_sdk/workbench/__main__.py
fraclab_sdk/workbench/pages/1_Snapshots.py
fraclab_sdk/workbench/pages/2_Browse.py
fraclab_sdk/workbench/pages/3_Selection.py
fraclab_sdk/workbench/pages/4_Run.py
fraclab_sdk/workbench/pages/5_Results.py
fraclab_sdk/workbench/pages/6_Algorithm_Edit.py
fraclab_sdk/workbench/pages/7_Schema_Edit.py
fraclab_sdk/workbench/pages/8_Output_Edit.py
fraclab_sdk/workbench/pages/9_Export_Algorithm.py
fraclab_sdk/workbench/pages/__init__.py
fraclab_sdk/workbench/ui_styles.py
fraclab_sdk/workbench/utils.py
fraclab_sdk-0.1.1.dist-info/METADATA
fraclab_sdk-0.1.1.dist-info/WHEEL
fraclab_sdk-0.1.1.dist-info/entry_points.txt
fraclab_sdk-0.1.1.dist-info/RECORD
