Metadata-Version: 2.4
Name: fraclab-sdk
Version: 0.1.1
Summary: SDK for managing snapshots, algorithms, and run execution
Requires-Python: >=3.11,<4.0
Classifier: Programming Language :: Python :: 3
Classifier: Programming Language :: Python :: 3.11
Classifier: Programming Language :: Python :: 3.12
Classifier: Programming Language :: Python :: 3.13
Classifier: Programming Language :: Python :: 3.14
Provides-Extra: workbench
Requires-Dist: fastapi (>=0.115.0,<0.116.0)
Requires-Dist: matplotlib (>=3.9.2,<4.0.0)
Requires-Dist: numpy (>=2.1.1,<3.0.0)
Requires-Dist: pandas (>=2.2.3,<3.0.0)
Requires-Dist: pyarrow (>=16.0.0) ; extra == "workbench"
Requires-Dist: pydantic (>=2.10.0,<3.0.0)
Requires-Dist: rich (>=13.9.0,<14.0.0)
Requires-Dist: scipy (>=1.13.1,<2.0.0)
Requires-Dist: streamlit (>=1.30) ; extra == "workbench"
Requires-Dist: typer (>=0.15.0,<0.16.0)
